ggrep/__init__.py
ggrep/cell.py
ggrep/cli.py
ggrep/col.py
ggrep/excel.py
ggrep/grid.py
ggrep/match.py
ggrep/row.py
ggrep-0.2.1.dist-info/METADATA
ggrep-0.2.1.dist-info/WHEEL
ggrep-0.2.1.dist-info/entry_points.txt
ggrep-0.2.1.dist-info/licenses/LICENSE
ggrep-0.2.1.dist-info/RECORD
